WindowsPingtaiXiaDeDuiYichuGeshihuaZifuchuanLoudongLiyongJishu/README.md
WindowsPingtaiXiaDeDuiYichuGeshihuaZifuchuanLoudongLiyongJishu/__init__.py
WindowsPingtaiXiaDeDuiYichuGeshihuaZifuchuanLoudongLiyongJishu/__main__.py
WindowsPingtaiXiaDeDuiYichuGeshihuaZifuchuanLoudongLiyongJishu/file.pdf
WindowsPingtaiXiaDeDuiYichuGeshihuaZifuchuanLoudongLiyongJishu/index.html
windows_pingtai_xia_de_dui_yichu_geshihua_zifuchuan_loudong_liyong_jishu-2024.3.2.0.dist-info/METADATA
windows_pingtai_xia_de_dui_yichu_geshihua_zifuchuan_loudong_liyong_jishu-2024.3.2.0.dist-info/WHEEL
windows_pingtai_xia_de_dui_yichu_geshihua_zifuchuan_loudong_liyong_jishu-2024.3.2.0.dist-info/entry_points.txt
windows_pingtai_xia_de_dui_yichu_geshihua_zifuchuan_loudong_liyong_jishu-2024.3.2.0.dist-info/top_level.txt
windows_pingtai_xia_de_dui_yichu_geshihua_zifuchuan_loudong_liyong_jishu-2024.3.2.0.dist-info/RECORD
